dictionaryx/__init__.py
dictionaryx/storage_providers/__init__.py
dictionaryx/storage_providers/example_provider.py.txt
dictionaryx-0.0.2.dist-info/WHEEL
dictionaryx-0.0.2.dist-info/METADATA
dictionaryx-0.0.2.dist-info/RECORD
