Metadata-Version: 2.1
Name: dictionaryx
Version: 0.0.2
Summary: 
Author: Dan Sikes
Author-email: dansikes7@gmail.com
Requires-Python: >=3.9,<4.0
Classifier: Programming Language :: Python :: 3
Classifier: Programming Language :: Python :: 3.9
Requires-Dist: msgpack (>=1.0.2,<2.0.0)
